validatable/__init__.py
validatable/engine.py
validatable/fields.py
validatable/generic_types.py
validatable/inference.py
validatable/main.py
validatable/type_dispatch.py
validatable/typing.py
validatable/version.py
validatable-0.4.0.dist-info/LICENSE
validatable-0.4.0.dist-info/METADATA
validatable-0.4.0.dist-info/WHEEL
validatable-0.4.0.dist-info/top_level.txt
validatable-0.4.0.dist-info/RECORD
