Metadata-Version: 2.1
Name: validatable
Version: 0.4.0
Summary: Validatable provides a single class definition for data validation and SQL table representation
Home-page: https://github.com/dcruzf/validatable
Author: Daniel França
Author-email: dcruzf.py@gmail.com
License: MIT
Platform: UNKNOWN
Classifier: Development Status :: 3 - Alpha
Classifier: Programming Language :: Python
Classifier: Programming Language :: Python :: 3
Classifier: Programming Language :: Python :: 3 :: Only
Classifier: Programming Language :: Python :: 3.6
Classifier: Programming Language :: Python :: 3.7
Classifier: Programming Language :: Python :: 3.8
Classifier: Programming Language :: Python :: 3.9
Classifier: Programming Language :: Python :: 3.10
Classifier: Intended Audience :: Developers
Classifier: Intended Audience :: Information Technology
Classifier: Intended Audience :: System Administrators
Classifier: License :: OSI Approved :: MIT License
Classifier: Operating System :: Unix
Classifier: Operating System :: POSIX :: Linux
Classifier: Environment :: Console
Classifier: Topic :: Software Development :: Libraries :: Python Modules
Classifier: Topic :: Internet
Requires-Python: >=3.6.1
Requires-Dist: pydantic (>=1.8)
Requires-Dist: sqlalchemy2-stubs
Requires-Dist: sqlalchemy (>=1.3)
Provides-Extra: email
Requires-Dist: email-validator (>=1.0.3) ; extra == 'email'
